datasense/__init__.py
datasense/data_access.py
datasense/data_analysis.py
datasense/data_plot.py
datasense/data_type.py
datasense/info.py
datasense-1.0.7.dist-info/LICENSE.txt
datasense-1.0.7.dist-info/METADATA
datasense-1.0.7.dist-info/WHEEL
datasense-1.0.7.dist-info/top_level.txt
datasense-1.0.7.dist-info/RECORD
